{
	"name": "Access Tunnel",
	"playerStart": {
		"x": 100,
		"y": 300
	},
	"blocks": [
		{"x": 15, "y": 585, "width": 770, "height": 15, "color": "red"},
		{"x": 15, "y": 400, "width": 200, "height": 15},
		{"x": 215, "y": 400, "width": 75, "height": 15, "color": "black"},
		{"x": 290, "y": 400, "width": 220, "height": 15},
		{"x": 390, "y": 150, "width": 20, "height": 250},
		{"x": 510, "y": 400, "width": 75, "height": 15, "color": "white"},
		{"x": 585, "y": 400, "width": 200, "height": 15},
		{"x": 670, "y": 400, "width": 100, "height": 15, "color": "gold"},
		
		{"x": 200, "y": 415, "width": 15, "height": 90, "color": "white"},
		{"x": 215, "y": 490, "width": 370, "height": 15, "color": "white"},
		{"x": 585, "y": 415, "width": 15, "height": 90, "color": "white"}
	],
	"hints": [
		{"x": 50, "y": 300, "text": "Some blocks won't budge\nwhen you change schemes"},
		{"x": 200, "y": 375, "color": "black", "text": "Some will disappear"},
		{"x": 230, "y": 510, "color": "white", "text": "Some will appear out of nowhere"},
		{"x": 425, "y": 375, "color": "white", "text": "Time this jump (and switch) carefully"}
	]
}